pyinitials/__init__.py
pyinitials/pyinitials.py
pyinitials-1.0.1.dist-info/LICENSE
pyinitials-1.0.1.dist-info/METADATA
pyinitials-1.0.1.dist-info/WHEEL
pyinitials-1.0.1.dist-info/RECORD
