Metadata-Version: 2.1
Name: pyinitials
Version: 1.0.1
Summary: 
License: ISC
Author: Rob van der Leek
Author-email: robvanderleek@gmail.com
Requires-Python: >=3.9,<4.0
Classifier: License :: OSI Approved
Classifier: Programming Language :: Python :: 3
Classifier: Programming Language :: Python :: 3.9
Classifier: Programming Language :: Python :: 3.10
Classifier: Programming Language :: Python :: 3.11
Classifier: Programming Language :: Python :: 3.12
Classifier: Programming Language :: Python :: 3.13
